nalibs/__init__.py
nalibs/addfunc.py
nalibs/utils_files.py
nalibs/utils_json.py
nalibs/utils_logger.py
nalibs/utils_yaml.py
nalibs-0.1.4.dist-info/LICENSE
nalibs-0.1.4.dist-info/METADATA
nalibs-0.1.4.dist-info/WHEEL
nalibs-0.1.4.dist-info/entry_points.txt
nalibs-0.1.4.dist-info/top_level.txt
nalibs-0.1.4.dist-info/RECORD
