Metadata-Version: 2.1
Name: nalibs
Version: 0.1.4
Summary: A small example package
Home-page: https://github.com/pypa/sampleproject
Author: Quang Nguyen
Author-email: anhquangnet@gmail.com
License: UNKNOWN
Platform: UNKNOWN
Classifier: Programming Language :: Python :: 3
Classifier: License :: OSI Approved :: MIT License
Classifier: Operating System :: OS Independent
Requires-Python: >=3.6
Requires-Dist: requests
Requires-Dist: PyYAML
